{
  "school_id": "illinois",
  "cfbd_name": "Illinois",
  "name": "Illinois",
  "mascot": "",
  "powerhouse_eras": [],
  "conferences": {},
  "coaches": [
    {
      "name": "Lovie Smith",
      "decade": "2010s",
      "coach_tier": "Sub-Par",
      "stats": {
        "stat_1": 15,
        "stat_2": 0,
        "stat_3": 0,
        "stat_4": 25,
        "stat_5": 17
      }
    },
    {
      "name": "Bret Bielema",
      "decade": "2020s",
      "coach_tier": "Standard",
      "stats": {
        "stat_1": 28,
        "stat_2": 0,
        "stat_3": 0,
        "stat_4": 50,
        "stat_5": 125
      }
    }
  ],
  "players": []
}
